ohbot/MotorDefinitionsv21.omd
ohbot/OhbotSettings.xml
ohbot/OhbotSpeech.csv
ohbot/Silence1.wav
ohbot/__init__.py
ohbot/ohbot.obe
ohbot/ohbot.py
ohbot/Images/calibrate400.gif
ohbot/Images/logoPT.gif
ohbot/Images/logoPTOH.gif
ohbot/Images/movedown.gif
ohbot/Images/moveright.gif
ohbot/Images/off.gif
ohbot/Images/offsmaller.gif
ohbot/Images/ohbotlogoSmall.gif
ohbot/Images/on.gif
ohbot/Images/onsmaller.gif
ohbot/Images/picohlogo.gif
ohbot/Images/picohlogoOn.gif
ohbot/Images/picohlogoSmall.gif
ohbot/Images/pixel.gif
ohbot/Images/plus.gif
ohbot/Images/resetIcon.gif
ohbot/Images/savebutton.gif
ohbot/Sounds/fanfare.wav
ohbot/Sounds/loop.wav
ohbot/Sounds/ohbot.wav
ohbot/Sounds/smash.wav
ohbot/Sounds/spring.wav
ohbot-4.0.16.dist-info/METADATA
ohbot-4.0.16.dist-info/WHEEL
ohbot-4.0.16.dist-info/top_level.txt
ohbot-4.0.16.dist-info/RECORD
